dns_poison_checker/__init__.py
dns_poison_checker/__main__.py
dns_poison_checker/poison_hosts
dns_poison_checker-0.1.0.dist-info/LICENSE
dns_poison_checker-0.1.0.dist-info/METADATA
dns_poison_checker-0.1.0.dist-info/WHEEL
dns_poison_checker-0.1.0.dist-info/entry_points.txt
dns_poison_checker-0.1.0.dist-info/RECORD
